LICENSE.txt
README.md
setup.cfg
setup.py
topsis/102153030.py
topsis/__init__.py
topsis_himanshu_102153030.egg-info/PKG-INFO
topsis_himanshu_102153030.egg-info/SOURCES.txt
topsis_himanshu_102153030.egg-info/dependency_links.txt
topsis_himanshu_102153030.egg-info/entry_points.txt
topsis_himanshu_102153030.egg-info/requires.txt
topsis_himanshu_102153030.egg-info/top_level.txt